git_installer/__init__.py
git_installer/core.py
git_installer-0.1.0.dist-info/LICENSE
git_installer-0.1.0.dist-info/METADATA
git_installer-0.1.0.dist-info/WHEEL
git_installer-0.1.0.dist-info/top_level.txt
git_installer-0.1.0.dist-info/RECORD
